{
	"format_version": "1.12.0",
	"minecraft:geometry": [
		{
			"description": {
				"identifier": "geometry.3in_flipflop",
				"texture_width": 64,
				"texture_height": 64,
				"visible_bounds_width": 3,
				"visible_bounds_height": 1.5,
				"visible_bounds_offset": [
					0,
					0.25,
					0
				]
			},
			"bones": [
				{
					"name": "basic_gate",
					"pivot": [
						7,
						0,
						-7
					],
					"cubes": [
						{
							"origin": [
								-3,
								1,
								-3
							],
							"size": [
								6,
								2,
								6
							],
							"uv": [
								0,
								36
							]
						},
						{
							"origin": [
								-3,
								0,
								-8
							],
							"size": [
								6,
								2,
								16
							],
							"uv": [
								0,
								0
							]
						},
						{
							"origin": [
								-2,
								0,
								-7
							],
							"size": [
								6,
								2,
								16
							],
							"pivot": [
								0,
								0,
								1
							],
							"rotation": [
								0,
								90,
								0
							],
							"uv": [
								0,
								18
							]
						}
					]
				},
				{
					"name": "SmallTorch2",
					"parent": "basic_gate",
					"pivot": [
						6,
						2,
						0
					],
					"cubes": [
						{
							"origin": [
								5,
								3,
								-1
							],
							"size": [
								2,
								2,
								2
							],
							"uv": [
								40,
								41
							]
						},
						{
							"origin": [
								5,
								2,
								-1
							],
							"size": [
								2,
								1,
								2
							],
							"uv": [
								44,
								0
							]
						}
					]
				},
				{
					"name": "BigTorch1",
					"parent": "basic_gate",
					"pivot": [
						-6,
						5,
						0
					],
					"cubes": [
						{
							"origin": [
								-7,
								5,
								-1
							],
							"size": [
								2,
								2,
								2
							],
							"uv": [
								24,
								41
							]
						},
						{
							"origin": [
								-7,
								2,
								-1
							],
							"size": [
								2,
								3,
								2
							],
							"uv": [
								24,
								36
							]
						}
					]
				},
				{
					"name": "BigTorch2",
					"parent": "basic_gate",
					"pivot": [
						0,
						5,
						6
					],
					"cubes": [
						{
							"origin": [
								-1,
								5,
								5
							],
							"size": [
								2,
								2,
								2
							],
							"uv": [
								32,
								41
							]
						},
						{
							"origin": [
								-1,
								2,
								5
							],
							"size": [
								2,
								3,
								2
							],
							"uv": [
								32,
								36
							]
						}
					]
				},
				{
					"name": "BigTorch3",
					"parent": "basic_gate",
					"pivot": [
						0,
						5,
						-6
					],
					"cubes": [
						{
							"origin": [
								-1,
								5,
								-7
							],
							"size": [
								2,
								2,
								2
							],
							"uv": [
								0,
								44
							]
						},
						{
							"origin": [
								-1,
								2,
								-7
							],
							"size": [
								2,
								3,
								2
							],
							"uv": [
								40,
								36
							]
						}
					]
				}
			]
		}
	]
}